xcs_rc/__init__.py
xcs_rc-1.3.3.dist-info/LICENSE
xcs_rc-1.3.3.dist-info/METADATA
xcs_rc-1.3.3.dist-info/WHEEL
xcs_rc-1.3.3.dist-info/top_level.txt
xcs_rc-1.3.3.dist-info/RECORD
