Metadata-Version: 2.1
Name: xcs-rc
Version: 1.3.3
Summary: Accuracy-based Learning Classifier Systems with Rule Combining
Author: Nugroho Fredivianus
Author-email: nuggfr@gmail.com
License: Free for non-commercial use
Keywords: machine learning,reinforcement learning,classifier systems,rule-based
Classifier: Programming Language :: Python :: 3
Classifier: Topic :: Scientific/Engineering :: Artificial Intelligence
Classifier: Operating System :: OS Independent
Classifier: License :: Free for non-commercial use
License-File: LICENSE
